entari_plugin_tsugu/__init__.py
entari_plugin_tsugu-0.1.7.dist-info/METADATA
entari_plugin_tsugu-0.1.7.dist-info/WHEEL
entari_plugin_tsugu-0.1.7.dist-info/top_level.txt
entari_plugin_tsugu-0.1.7.dist-info/RECORD
