Metadata-Version: 2.4
Name: entari_plugin_tsugu
Version: 0.1.7
Summary: Tsugu BanGDream Bot
Author-email: kumoSleeping <zjr2992@outlook.com>
License: MIT
Project-URL: Homepage, https://github.com/kumoSleeping/entari-plugin-tsugu
Project-URL: Repository, https://github.com/kumoSleeping/entari-plugin-tsugu
Project-URL: Issues, https://github.com/kumoSleeping/entari-plugin-tsugu/issues
Keywords: entari,tsugu,bangdream,bot
Classifier: Development Status :: 3 - Alpha
Classifier: Intended Audience :: Developers
Classifier: License :: OSI Approved :: MIT License
Classifier: Programming Language :: Python :: 3
Classifier: Programming Language :: Python :: 3.11
Classifier: Programming Language :: Python :: 3.12
Requires-Python: >=3.8
Requires-Dist: arclet.entari[cron,dotenv,reload,yaml]>=0.14.1
Requires-Dist: tsugu>=6.4.0
